matflow/__init__.py
matflow/_version.py
matflow/api.py
matflow/cli.py
matflow/config.py
matflow/errors.py
matflow/extensions.py
matflow/hicklable.py
matflow/profile.py
matflow/scripting.py
matflow/utils.py
matflow/validation.py
matflow/models/__init__.py
matflow/models/command.py
matflow/models/construction.py
matflow/models/element.py
matflow/models/parameters.py
matflow/models/software.py
matflow/models/task.py
matflow/models/workflow.py
tests/__init__.py
tests/test_element_idx.py
tests/test_hicklable.py
tests/test_task.py
tests/test_workflow.py
matflow-0.2.27.dist-info/LICENSE
matflow-0.2.27.dist-info/METADATA
matflow-0.2.27.dist-info/WHEEL
matflow-0.2.27.dist-info/entry_points.txt
matflow-0.2.27.dist-info/top_level.txt
matflow-0.2.27.dist-info/RECORD
