Metadata-Version: 2.1
Name: matflow
Version: 0.2.27
Summary: Computational workflow management for materials science.
Home-page: UNKNOWN
Author: Adam J. Plowman
Author-email: adam.plowman@manchester.ac.uk
License: UNKNOWN
Project-URL: Github, https://github.com/Lightform-group/matflow
Platform: UNKNOWN
Classifier: Development Status :: 3 - Alpha
Classifier: Intended Audience :: Science/Research
Classifier: Topic :: Scientific/Engineering
Classifier: Programming Language :: Python :: 3.7
Classifier: Programming Language :: Python :: 3.8
Classifier: License :: OSI Approved :: Mozilla Public License 2.0 (MPL 2.0)
Classifier: Operating System :: OS Independent
Requires-Dist: matflow-demo-extension
Requires-Dist: hpcflow >=0.1.16
Requires-Dist: click >7.0
Requires-Dist: hickle ==4.0.4
Requires-Dist: h5py ==2.10.0
Requires-Dist: numpy <1.24
Requires-Dist: sqlalchemy <2
Requires-Dist: ruamel.yaml ==0.16.10
Requires-Dist: pyperclip
Requires-Dist: black
Requires-Dist: autopep8
